tomogram_shift_alignment/__init__.py
tomogram_shift_alignment/apply_shifts.py
tomogram_shift_alignment/run_corrsearch3d.py
tomogram_shift_alignment/tomogram_shift_alignment.py
tomogram_shift_alignment/version.py
tomogram_shift_alignment-0.0.1.dist-info/LICENSE
tomogram_shift_alignment-0.0.1.dist-info/METADATA
tomogram_shift_alignment-0.0.1.dist-info/WHEEL
tomogram_shift_alignment-0.0.1.dist-info/entry_points.txt
tomogram_shift_alignment-0.0.1.dist-info/top_level.txt
tomogram_shift_alignment-0.0.1.dist-info/RECORD
