Metadata-Version: 2.1
Name: tomogram-shift-alignment
Version: 0.0.1
Summary: Program to compare the shifts between two of the same tomogram which were constructed by different TSA methods, and to adjust the particle coordinates of a star file to fit the new tomogram.
Home-page: https://github.com/EuanPyle/tomogram_shift_alignment
Author: Euan Pyle
License: MIT License
Project-URL: Source Code, https://github.com/EuanPyle/tomogram_shift_alignment
Platform: UNKNOWN
Classifier: Development Status :: 2 - Pre-Alpha
Classifier: Natural Language :: English
Classifier: Programming Language :: Python :: 3
Classifier: Programming Language :: Python :: 3.7
Classifier: Programming Language :: Python :: 3.8
Classifier: Programming Language :: Python :: 3.9
Requires-Python: >=3.7
License-File: LICENSE
Requires-Dist: numpy
Requires-Dist: click (==8.0.4)
Requires-Dist: starfile
Requires-Dist: pandas
Requires-Dist: thefuzz
Requires-Dist: setuptools-scm
Requires-Dist: typer
Requires-Dist: mrcfile
Requires-Dist: python-Levenshtein
